README.txt
setup.py
esFrontLine/__init__.py
esFrontLine/app.py
esFrontLine/auth.py
esFrontLine.egg-info/PKG-INFO
esFrontLine.egg-info/SOURCES.txt
esFrontLine.egg-info/dependency_links.txt
esFrontLine.egg-info/entry_points.txt
esFrontLine.egg-info/not-zip-safe
esFrontLine.egg-info/requires.txt
esFrontLine.egg-info/top_level.txt
esFrontLine/client/__init__.py
esFrontLine/client/async.py
esFrontLine/client/base.py
esFrontLine/client/sync.py