Metadata-Version: 1.1
Name: esFrontLine
Version: 2.11.18154
Summary: Limit restful requests to backend ElasticSearch cluster:  Queries only.
Home-page: https://github.com/klahnakoski/esFrontLine
Author: Kyle Lahnakoski
Author-email: kyle@lahnakoski.com
License: MPL 2.0
Platform: UNKNOWN
Classifier: Development Status :: 4 - Beta
Classifier: Topic :: Internet :: Proxy Servers
Classifier: License :: OSI Approved :: Mozilla Public License 2.0 (MPL 2.0)
Classifier: Programming Language :: Python :: 3.6
Classifier: Programming Language :: Python :: 2.7
